tracardi_time_blocker/time_blocker_action.py
tracardi_time_blocker-0.1.1.dist-info/METADATA
tracardi_time_blocker-0.1.1.dist-info/WHEEL
tracardi_time_blocker-0.1.1.dist-info/top_level.txt
tracardi_time_blocker-0.1.1.dist-info/RECORD
